sardine/__init__.py
sardine/buffer/__init__.py
sardine/buffer/base_vec_env.py
sardine/buffer/buffers.py
sardine/buffer/type_aliases.py
sardine/buffer/utils.py
sardine/buffer/vec_normalize.py
sardine/consts.py
sardine/embeddings/item_embeddings_focused_small.npy
sardine/embeddings/item_embeddings_rerank.npy
sardine/embeddings/mf_embeddings/SlateTopK-Bored-v0_epsilon0.5_seed2023.npy
sardine/policies/__init__.py
sardine/policies/base.py
sardine/policies/epsilon_oracles.py
sardine/simulator.py
sardine/version.py
sardine/wrappers/__init__.py
sardine/wrappers/ideal_state.py
sardine/wrappers/topk.py
sardine_rec-1.0.8.dist-info/LICENSE
sardine_rec-1.0.8.dist-info/METADATA
sardine_rec-1.0.8.dist-info/WHEEL
sardine_rec-1.0.8.dist-info/RECORD
