Metadata-Version: 2.1
Name: sardine-rec
Version: 1.0.8
Summary: a Simulator for Automated Recommendation in Dynamic and INteractive Environments
Home-page: https://github.com/naver/sardine
License: MIT
Author: Romain Deffayet
Author-email: romain.deffayet@naverlabs.com
Requires-Python: >=3.9,<4.0
Classifier: License :: OSI Approved :: MIT License
Classifier: Programming Language :: Python :: 3
Classifier: Programming Language :: Python :: 3.9
Classifier: Programming Language :: Python :: 3.10
Classifier: Programming Language :: Python :: 3.11
Classifier: Programming Language :: Python :: 3.12
Requires-Dist: gymnasium (>=0.28)
Project-URL: Repository, https://github.com/naver/sardine
